kfp_local/__init__.py
kfp_local/client.py
kfp_local/local_client.py
kfp_local/.idea/idea.py
kfp_py_func_local-0.0.2.dist-info/METADATA
kfp_py_func_local-0.0.2.dist-info/WHEEL
kfp_py_func_local-0.0.2.dist-info/entry_points.txt
kfp_py_func_local-0.0.2.dist-info/top_level.txt
kfp_py_func_local-0.0.2.dist-info/RECORD
