Metadata-Version: 2.1
Name: kfp-py-func-local
Version: 0.0.2
Summary: kfp-py-func-local
Home-page: http://github.com/iuiu34/kfp-py-func-local
Author: iuiu34
Author-email: 
License: COPYRIGHT
Keywords: kubeflow,local,py-func
Platform: UNKNOWN
Classifier: Development Status :: 2 - Pre-Alpha
Classifier: Programming Language :: Python :: 3 :: Only
Classifier: Programming Language :: Python :: 3.6
Requires-Dist: fire
